LICENSE
README.md
setup.cfg
setup.py
socialforce/__init__.py
socialforce/field_of_view.py
socialforce/scenarios.py
socialforce/show.py
socialforce/simulator.py
socialforce/stateutils.py
socialforce/trainer.py
socialforce/trajnet.py
socialforce.egg-info/PKG-INFO
socialforce.egg-info/SOURCES.txt
socialforce.egg-info/dependency_links.txt
socialforce.egg-info/requires.txt
socialforce.egg-info/top_level.txt
socialforce/potentials/__init__.py
socialforce/potentials/pedped_1d.py
socialforce/potentials/pedped_2d.py
socialforce/potentials/pedspace.py